pybelt/__init__.py
pybelt/_communication_interface.py
pybelt/_gatt_profile.py
pybelt/belt_controller.py
pybelt/belt_scanner.py
pybelt/examples_utility.py
pybelt/examples_utility_getch.py
pybelt/__pycache__/__init__.cpython-37.pyc
pybelt/__pycache__/_communication_interface.cpython-37.pyc
pybelt-1.2.4.dist-info/LICENSE
pybelt-1.2.4.dist-info/METADATA
pybelt-1.2.4.dist-info/WHEEL
pybelt-1.2.4.dist-info/top_level.txt
pybelt-1.2.4.dist-info/RECORD
