Metadata-Version: 2.1
Name: pybelt
Version: 1.2.4
Summary: An Python library to control the feelSpace naviBelt from your application
Home-page: https://github.com/feelSpace/pybelt
Author: feelSpace GmbH
Author-email: dev@feelspace.de
Classifier: Programming Language :: Python :: 3
Classifier: License :: OSI Approved :: Apache Software License
Classifier: Operating System :: OS Independent
Requires-Python: >=3.3
License-File: LICENSE
Requires-Dist: pyserial
Requires-Dist: bleak
